Products.Archetypes-1.16.5-py2.7-nspkg.pth
Products/Archetypes/AUTHORS
Products/Archetypes/AllowedTypesByIface.py
Products/Archetypes/ArchetypeTool.py
Products/Archetypes/BaseBTreeFolder.py
Products/Archetypes/BaseContent.py
Products/Archetypes/BaseFolder.py
Products/Archetypes/BaseObject.py
Products/Archetypes/BaseUnit.py
Products/Archetypes/CatalogMultiplex.py
Products/Archetypes/ClassGen.py
Products/Archetypes/ExtensibleMetadata.py
Products/Archetypes/Field.py
Products/Archetypes/Layer.py
Products/Archetypes/Marshall.py
Products/Archetypes/OrderedBaseFolder.py
Products/Archetypes/ReferenceEngine.py
Products/Archetypes/Referenceable.py
Products/Archetypes/Registry.py
Products/Archetypes/Renderer.py
Products/Archetypes/SQLMethod.py
Products/Archetypes/SQLStorage.py
Products/Archetypes/SQLStorageConfig.py
Products/Archetypes/TemplateMixin.py
Products/Archetypes/UIDCatalog.py
Products/Archetypes/VariableSchemaSupport.py
Products/Archetypes/WebDAVSupport.py
Products/Archetypes/Widget.py
Products/Archetypes/__init__.py
Products/Archetypes/annotations.py
Products/Archetypes/atapi.py
Products/Archetypes/athistoryaware.py
Products/Archetypes/bbb.py
Products/Archetypes/bridge.zcml
Products/Archetypes/config.py
Products/Archetypes/configure.zcml
Products/Archetypes/debug.py
Products/Archetypes/event.py
Products/Archetypes/events.zcml
Products/Archetypes/exceptions.py
Products/Archetypes/fieldproperty.py
Products/Archetypes/implements.zcml
Products/Archetypes/log.py
Products/Archetypes/mimetype_utils.py
Products/Archetypes/profiles.zcml
Products/Archetypes/public.py
Products/Archetypes/references.py
Products/Archetypes/setuphandlers.py
Products/Archetypes/subscribers.py
Products/Archetypes/tool.gif
Products/Archetypes/traverse.py
Products/Archetypes/utils.py
Products/Archetypes/uuid.py
Products/Archetypes/validator.py
Products/Archetypes/Extensions/__init__.py
Products/Archetypes/Extensions/migrations.py
Products/Archetypes/Extensions/utils.py
Products.Archetypes-1.16.5.dist-info/METADATA
Products.Archetypes-1.16.5.dist-info/WHEEL
Products.Archetypes-1.16.5.dist-info/namespace_packages.txt
Products.Archetypes-1.16.5.dist-info/top_level.txt
Products.Archetypes-1.16.5.dist-info/RECORD
