Metadata-Version: 2.1
Name: Products.Archetypes
Version: 1.16.5
Summary: Archetypes is a developers framework for rapidly developing and deploying rich, full featured content types within the context of Zope/CMF and Plone.
Home-page: https://pypi.org/project/Products.Archetypes
Author: Archetypes development team
Author-email: plone-developers@lists.sourceforge.net
License: GPL
Keywords: Archetypes Plone CMF Zope
Platform: UNKNOWN
Classifier: Development Status :: 6 - Mature
Classifier: Framework :: Plone
Classifier: Framework :: Plone :: 5.2
Classifier: Framework :: Zope2
Classifier: Framework :: Zope :: 4
Classifier: License :: OSI Approved :: GNU General Public License (GPL)
Classifier: Programming Language :: Python
Classifier: Programming Language :: Python :: 2.7
Requires-Dist: setuptools
Requires-Dist: zope.component
Requires-Dist: zope.contenttype
Requires-Dist: zope.datetime
Requires-Dist: zope.deferredimport
Requires-Dist: zope.event
Requires-Dist: zope.i18n
Requires-Dist: zope.i18nmessageid
Requires-Dist: zope.interface
Requires-Dist: zope.lifecycleevent
Requires-Dist: zope.publisher
Requires-Dist: zope.schema
Requires-Dist: zope.tal
Requires-Dist: zope.viewlet
Requires-Dist: Products.CMFCore
Requires-Dist: Products.CMFFormController
Requires-Dist: Products.DCWorkflow
Requires-Dist: Products.GenericSetup (>=1.8.3)
Requires-Dist: Products.MimetypesRegistry (>=2.0.3)
Requires-Dist: Products.PortalTransforms
Requires-Dist: Products.ZSQLMethods
Requires-Dist: Products.statusmessages
Requires-Dist: Products.validation
Requires-Dist: plone.folder
Requires-Dist: plone.uuid
Requires-Dist: plone.app.folder
Requires-Dist: Acquisition
Requires-Dist: DateTime
Requires-Dist: ExtensionClass
Requires-Dist: transaction
Requires-Dist: ZODB3
Requires-Dist: Zope (>=4.0b7.dev0)
Requires-Dist: Zope2
Requires-Dist: plone.app.widgets (>=2.0.0.dev0)
Provides-Extra: test
Requires-Dist: zope.annotation ; extra == 'test'
Requires-Dist: zope.publisher ; extra == 'test'
Requires-Dist: zope.testing ; extra == 'test'
Requires-Dist: plone.app.testing ; extra == 'test'
Requires-Dist: Products.ATContentTypes ; extra == 'test'
Requires-Dist: mock ; extra == 'test'
Requires-Dist: plone.app.robotframework ; extra == 'test'
